PyRoutine/__init__.py
PyRoutine/click.py
PyRoutine/track.py
PyRoutine-1.3.0.dist-info/LICENSE
PyRoutine-1.3.0.dist-info/METADATA
PyRoutine-1.3.0.dist-info/WHEEL
PyRoutine-1.3.0.dist-info/top_level.txt
PyRoutine-1.3.0.dist-info/RECORD
