Metadata-Version: 2.1
Name: PyRoutine
Version: 1.3.0
Summary: A program to redo mouse functions.
Home-page: https://github.com/Atharv2/PyRoutine
Author: Atharv2
Author-email: atharv260107@gmail.com
License: UNKNOWN
Platform: UNKNOWN
Classifier: Programming Language :: Python :: 3
Classifier: License :: OSI Approved :: GNU General Public License v3 (GPLv3)
Classifier: Operating System :: OS Independent
Requires-Python: >=3.0
